my_library/VERSION.txt
my_library/__init__.py
my_library/functions.py
my_library-0.0.1.dist-info/LICENSE
my_library-0.0.1.dist-info/METADATA
my_library-0.0.1.dist-info/WHEEL
my_library-0.0.1.dist-info/top_level.txt
my_library-0.0.1.dist-info/RECORD
